LICENSE
MANIFEST.in
README.rst
VERSION
setup.py
Lid.egg-info/PKG-INFO
Lid.egg-info/SOURCES.txt
Lid.egg-info/dependency_links.txt
Lid.egg-info/top_level.txt
src/__init__.py
src/databases/__init__.py
src/log/__init__.py
src/log/log.py
src/log/interface/__init__.py
src/log/interface/database.py
src/log/interface/file.py
src/log/interface/stream.py