Metadata-Version: 1.1
Name: Lid
Version: 1.0.4
Summary: tiny project
Home-page: http://blog.owlsn.com
Author: zouhao
Author-email: helloworld.zouhao@gmail.com
License: MIT License
Keywords: lid,python3
Platform: any
Classifier: Development Status :: 1 - Planning
